__init__.py
stopwatch.py
textual_stopwatch_tutorial_jt-0.0.1.dist-info/licenses/LICENSE.txt
textual_stopwatch_tutorial_jt-0.0.1.dist-info/METADATA
textual_stopwatch_tutorial_jt-0.0.1.dist-info/WHEEL
textual_stopwatch_tutorial_jt-0.0.1.dist-info/top_level.txt
textual_stopwatch_tutorial_jt-0.0.1.dist-info/RECORD
