Metadata-Version: 2.4
Name: textual_stopwatch_tutorial_JT
Version: 0.0.1
Summary: My completed textual tutorial
Author-email: Jackson Taylor <jackson.taylor.2003@gmail.com>
License-Expression: MIT
Project-URL: TextualWebsite, https://textual.textualize.io/tutorial/#writing-textual-css
Classifier: Programming Language :: Python :: 3
Classifier: Operating System :: OS Independent
Requires-Python: >=3.13.5
License-File: LICENSE.txt
Requires-Dist: textual
Dynamic: license-file
